app/__init__.py
app/__main__.py
app/config.py
app/server.py
app/tracing.py
app/models/__init__.py
app/models/building.py
app/prompts/__init__.py
app/store/__init__.py
app/store/database.py
app/tools/__init__.py
app/tools/cache.py
app/tools/context.py
app/tools/esg.py
app/tools/health.py
app/tools/secrets.py
app/tools/sustainability.py
real_estate_sustainability_mcp-0.0.2.dist-info/METADATA
real_estate_sustainability_mcp-0.0.2.dist-info/WHEEL
real_estate_sustainability_mcp-0.0.2.dist-info/entry_points.txt
real_estate_sustainability_mcp-0.0.2.dist-info/licenses/LICENSE
real_estate_sustainability_mcp-0.0.2.dist-info/RECORD
