Metadata-Version: 2.4
Name: real-estate-sustainability-mcp
Version: 0.0.2
Summary: MCP server for analyzing building sustainability metrics through Excel, PDF, and standardized frameworks (ESG, LEED, BREEAM, DGNB) with IFC integration
Author-email: Luke <luke@example.com>
License-File: LICENSE
Requires-Python: >=3.12
Requires-Dist: fastmcp>=2.14.0
Requires-Dist: langfuse>=3.10.0
Requires-Dist: mcp-refcache>=0.1.0
Requires-Dist: pydantic-settings>=2.10.0
Requires-Dist: pydantic>=2.10.0
Requires-Dist: typer>=0.15.0
